termichess/__init__.py
termichess/__main__.py
termichess/app.py
termichess/chess_board.py
termichess/config_screen.py
termichess/promotion.py
termichess/sidebar.py
termichess/utils.py
termichess/assets/__init__.py
termichess/assets/pieces/asciiart/__init__.py
termichess/assets/pieces/asciiart/basic.py
termichess/assets/pieces/asciiart/char.py
termichess/assets/pieces/asciiart/computer_first.py
termichess/assets/pieces/asciiart/computer_second.py
termichess/assets/pieces/asciiart/computer_third.py
termichess/assets/pieces/asciiart/geometric.py
termichess/assets/pieces/asciiart/glyph.py
termichess/assets/pieces/asciiart/got.py
termichess/assets/pieces/asciiart/mahabharat.py
termichess/assets/pieces/asciiart/minimalistic.py
termichess/assets/pieces/asciiart/potter.py
termichess/assets/pieces/asciiart/rad.py
termichess/assets/pieces/asciiart/retro.py
termichess/assets/pieces/asciiart/scientist.py
termichess/assets/pieces/asciiart/shaded.py
termichess/assets/pieces/v1/black_bishop.png
termichess/assets/pieces/v1/black_king.png
termichess/assets/pieces/v1/black_knight.png
termichess/assets/pieces/v1/black_pawn.png
termichess/assets/pieces/v1/black_queen.png
termichess/assets/pieces/v1/black_rook.png
termichess/assets/pieces/v1/white_bishop.png
termichess/assets/pieces/v1/white_king.png
termichess/assets/pieces/v1/white_knight.png
termichess/assets/pieces/v1/white_pawn.png
termichess/assets/pieces/v1/white_queen.png
termichess/assets/pieces/v1/white_rook.png
termichess/assets/sound/check.wav
termichess/assets/sound/move.wav
termichess/piece_generator/create_pieces.py
termichess-0.1.4.dist-info/LICENSE
termichess-0.1.4.dist-info/METADATA
termichess-0.1.4.dist-info/WHEEL
termichess-0.1.4.dist-info/entry_points.txt
termichess-0.1.4.dist-info/top_level.txt
termichess-0.1.4.dist-info/RECORD
