Metadata-Version: 2.1
Name: termichess
Version: 0.1.4
Summary: A chess game on your terminal
Home-page: https://github.com/whiletruelearn/termichess
Author: Krishna Sangeeth KS
Author-email: kskrishnasangeeth@gmail.com
Classifier: Programming Language :: Python :: 3
Classifier: License :: OSI Approved :: MIT License
Classifier: Operating System :: OS Independent
Requires-Python: >=3.10
License-File: LICENSE
Requires-Dist: textual==0.82.0
Requires-Dist: pillow==10.3.0
Requires-Dist: chess==1.11.0
Requires-Dist: rich-pixels==3.0.1
Requires-Dist: simpleaudio==1.0.4
